statisticsmmm/__init__.py
statisticsmmm/data.py
statisticsmmm/meanmedianmodeclc.py
statisticsmmm-0.1.dist-info/LICENSE.txt.txt
statisticsmmm-0.1.dist-info/METADATA
statisticsmmm-0.1.dist-info/WHEEL
statisticsmmm-0.1.dist-info/top_level.txt
statisticsmmm-0.1.dist-info/RECORD
