Metadata-Version: 2.1
Name: statisticsmmm
Version: 0.1
Summary: This helps in finding mean, median, mode of a given list of data
Author: Subba Lakshmi R K
Author-email: rksubbalakshmi@gmail.com
Classifier: Programming Language :: Python :: 3.10
Classifier: License :: OSI Approved :: MIT License
Classifier: Operating System :: OS Independent
License-File: LICENSE.txt.txt
